webhookit/__init__.py
webhookit/app.py
webhookit/cli.py
webhookit/parser.py
webhookit/temp.py
webhookit/utils.py
webhookit3-0.1.1.dist-info/LICENSE
webhookit3-0.1.1.dist-info/METADATA
webhookit3-0.1.1.dist-info/WHEEL
webhookit3-0.1.1.dist-info/entry_points.txt
webhookit3-0.1.1.dist-info/top_level.txt
webhookit3-0.1.1.dist-info/RECORD
