Metadata-Version: 2.1
Name: webhookit3
Version: 0.1.1
Summary: Bind git webhooks with actions. Simple git webhook cli tool for automation tasks.
Home-page: https://github.com/18438655078/webhookit3
Author: lihd
Author-email: UNKNOWN
License: MIT
Keywords: webhookit,webhook,github,gitlab,gogs,git-webhook
Platform: UNKNOWN
Classifier: Intended Audience :: Developers
Classifier: Operating System :: OS Independent
Classifier: Natural Language :: Chinese (Simplified)
Classifier: Programming Language :: Python
Classifier: Programming Language :: Python :: 2
Classifier: Programming Language :: Python :: 2.5
Classifier: Programming Language :: Python :: 2.6
Classifier: Programming Language :: Python :: 2.7
Classifier: Programming Language :: Python :: 3
Classifier: Programming Language :: Python :: 3.3
Classifier: Programming Language :: Python :: 3.4
Classifier: Programming Language :: Python :: 3.5
Classifier: Programming Language :: Python :: 3.6
Classifier: Topic :: Utilities
Requires-Dist: click
Requires-Dist: tornado
Requires-Dist: paramiko
